byted_overpass_flow_devops_oncall/__init__.py
byted_overpass_flow_devops_oncall-0.0.1.dist-info/METADATA
byted_overpass_flow_devops_oncall-0.0.1.dist-info/WHEEL
byted_overpass_flow_devops_oncall-0.0.1.dist-info/top_level.txt
byted_overpass_flow_devops_oncall-0.0.1.dist-info/RECORD
